[
	{
		"aid": "0",
		"text": "Dengan nama Allah Yang Maha Pengasih, Maha Penyayang."
	},
	{
		"aid": "1",
		"p": "op",
		"text": "[Allah] Yang Maha Pengasih,"
	},
	{
		"aid": "2",
		"text": "Yang telah mengajarkan Alquran."
	},
	{
		"aid": "3",
		"text": "Dia menciptakan manusia,"
	},
	{
		"aid": "4",
		"p": "cp",
		"text": "mengajarnya pandai berbicara."
	},
	{
		"aid": "5",
		"p": "op",
		"text": "Matahari dan bulan beredar menurut perhitungan,"
	},
	{
		"aid": "6",
		"text": "dan tetumbuhan dan pepohonan, keduanya tunduk (kepada-Nya)."
	},
	{
		"aid": "7",
		"text": "Dan langit telah ditinggikan-Nya dan Dia ciptakan keseimbangan,"
	},
	{
		"aid": "8",
		"text": "agar kamu jangan merusak keseimbangan itu."
	},
	{
		"aid": "9",
		"p": "cp",
		"text": "Dan tegakkanlah keseimbangan itu dengan adil dan janganlah kamu mengurangi keseimbangan itu."
	},
	{
		"aid": "10",
		"p": "op",
		"text": "Dan bumi telah dibentangkan-Nya untuk makhluk[-Nya],"
	},
	{
		"aid": "11",
		"text": "di dalamnya ada buah-buahan dan pohon kurma yang mempunyai kelopak mayang,"
	},
	{
		"aid": "12",
		"text": "dan biji-bijian yang berkulit dan bunga-bunga yang harum baunya."
	},
	{
		"aid": "13",
		"p": "cp",
		"text": "Maka nikmat Tuhanmu yang manakah yang kamu dustakan?"
	},
	{
		"aid": "14",
		"p": "op",
		"text": "Dia menciptakan manusia dari tanah kering seperti tembikar,"
	},
	{
		"aid": "15",
		"text": "dan Dia menciptakan jin dari nyala api tanpa asap."
	},
	{
		"aid": "16",
		"p": "cp",
		"text": "Maka nikmat Tuhanmu yang manakah yang kamu dustakan?"
	},
	{
		"aid": "17",
		"p": "op",
		"text": "Tuhan [yang memelihara] dua timur dan Tuhan [yang memelihara] dua barat."
	},
	{
		"aid": "18",
		"p": "cp",
		"text": "Maka nikmat Tuhanmu yang manakah yang kamu dustakan?"
	},
	{
		"aid": "19",
		"p": "op",
		"text": "Dia membiarkan dua laut mengalir yang [kemudian] keduanya bertemu,"
	},
	{
		"aid": "20",
		"text": "di antara keduanya ada batas yang tidak dilampaui oleh masing-masing."
	},
	{
		"aid": "21",
		"text": "Maka nikmat Tuhanmu yang manakah yang kamu dustakan?"
	},
	{
		"aid": "22",
		"p": "nl",
		"text": "Dari keduanya keluar mutiara dan marjan."
	},
	{
		"aid": "23",
		"p": "cp",
		"text": "Maka nikmat Tuhanmu yang manakah yang kamu dustakan?"
	},
	{
		"aid": "24",
		"p": "op",
		"text": "Milik-Nyalah kapal-kapal yang berlayar di lautan bagaikan gunung-gunung."
	},
	{
		"aid": "25",
		"p": "cp",
		"r": "1",
		"text": "Maka nikmat Tuhanmu yang manakah yang kamu dustakan?"
	},
	{
		"aid": "26",
		"p": "op",
		"text": "Semua yang ada di bumi itu akan binasa,"
	},
	{
		"aid": "27",
		"text": "tetapi wajah Tuhanmu yang memiliki kebesaran dan kemuliaan tetap kekal."
	},
	{
		"aid": "28",
		"p": "cp",
		"text": "Maka nikmat Tuhanmu yang manakah yang kamu dustakan?"
	},
	{
		"aid": "29",
		"p": "op",
		"text": "Apa yang di langit dan di bumi selalu meminta kepada-Nya. Setiap waktu Dia dalam kesibukan."
	},
	{
		"aid": "30",
		"text": "Maka nikmat Tuhanmu yang manakah yang kamu dustakan?"
	},
	{
		"aid": "31",
		"p": "nl",
		"text": "Kami akan memberi perhatian sepenuhnya kepadamu wahai [golongan] manusia dan jin!"
	},
	{
		"aid": "32",
		"p": "cp",
		"text": "Maka nikmat Tuhanmu yang manakah yang kamu dustakan?"
	},
	{
		"aid": "33",
		"p": "op",
		"text": "Wahai golongan jin dan manusia! Jika kamu sanggup menembus (melintasi) penjuru langit dan bumi, maka tembuslah. Kamu tidak akan mampu menembusnya kecuali dengan kekuatan [dari Allah]."
	},
	{
		"aid": "34",
		"p": "cp",
		"text": "Maka nikmat Tuhanmu yang manakah yang kamu dustakan?"
	},
	{
		"aid": "35",
		"p": "op",
		"text": "Kepada kamu (jin dan manusia), akan dikirim nyala api dan cairan tembaga [panas] sehingga kamu tidak dapat menyelamatkan diri [darinya]."
	},
	{
		"aid": "36",
		"p": "cp",
		"text": "Maka nikmat Tuhanmu yang manakah yang kamu dustakan?"
	},
	{
		"aid": "37",
		"p": "op",
		"text": "Maka apabila langit telah terbelah dan menjadi merah mawar seperti [kilauan] minyak."
	},
	{
		"aid": "38",
		"text": "Maka nikmat Tuhanmu yang manakah yang kamu dustakan?"
	},
	{
		"aid": "39",
		"p": "nl",
		"text": "Maka pada hari itu manusia dan jin tidak ditanya tentang dosanya."
	},
	{
		"aid": "40",
		"p": "cp",
		"text": "Maka nikmat Tuhanmu yang manakah yang kamu dustakan?"
	},
	{
		"aid": "41",
		"p": "op",
		"text": "Orang-orang yang berdosa itu diketahui dengan tanda-tandanya, lalu direnggut ubun-ubun dan kakinya."
	},
	{
		"aid": "42",
		"text": "Maka nikmat Tuhanmu yang manakah yang kamu dustakan?"
	},
	{
		"aid": "43",
		"p": "nl",
		"text": "Inilah neraka Jahanam yang didustakan oleh orang-orang berdosa."
	},
	{
		"aid": "44",
		"text": "Mereka berkeliling di sana dan di antara air yang mendidih."
	},
	{
		"aid": "45",
		"p": "cp",
		"r": "2",
		"text": "Maka nikmat Tuhanmu yang manakah yang kamu dustakan?"
	},
	{
		"aid": "46",
		"p": "op",
		"text": "Dan bagi siapa yang takut akan saat menghadap Tuhannya ada dua surga."
	},
	{
		"aid": "47",
		"text": "Maka nikmat Tuhanmu yang manakah yang kamu dustakan?"
	},
	{
		"aid": "48",
		"p": "nl",
		"text": "Kedua surga itu mempunyai aneka pepohonan dan buah-buahan."
	},
	{
		"aid": "49",
		"text": "Maka nikmat Tuhanmu yang manakah yang kamu dustakan?"
	},
	{
		"aid": "50",
		"p": "nl",
		"text": "Di dalam kedua surga itu ada dua buah mata air yang memancar."
	},
	{
		"aid": "51",
		"text": "Maka nikmat Tuhanmu yang manakah yang kamu dustakan?"
	},
	{
		"aid": "52",
		"p": "nl",
		"text": "Di dalam kedua surga itu terdapat aneka buah-buahan yang berpasang-pasangan."
	},
	{
		"aid": "53",
		"text": "Maka nikmat Tuhanmu yang manakah yang kamu dustakan?"
	},
	{
		"aid": "54",
		"p": "nl",
		"text": "Mereka bersandar di atas permadani yang bagian dalamnya dari sutera tebal. Dan buah-buahan di kedua surga itu dapat [dipetik] dari dekat."
	},
	{
		"aid": "55",
		"p": "cp",
		"text": "Maka nikmat Tuhanmu yang manakah yang kamu dustakan?"
	},
	{
		"aid": "56",
		"p": "op",
		"text": "Di dalam surga itu ada bidadari-bidadari yang membatasi pandangan, tidak pernah disentuh oleh manusia maupun jin sebelumnya."
	},
	{
		"aid": "57",
		"text": "Maka nikmat Tuhanmu yang manakah yang kamu dustakan?"
	},
	{
		"aid": "58",
		"p": "nl",
		"text": "Seakan-akan mereka itu permata yakut dan marjan."
	},
	{
		"aid": "59",
		"p": "cp",
		"text": "Maka nikmat Tuhanmu yang manakah yang kamu dustakan?"
	},
	{
		"aid": "60",
		"p": "op",
		"text": "Tidak ada balasan untuk kebaikan selain kebaikan [pula]."
	},
	{
		"aid": "61",
		"p": "cp",
		"text": "Maka nikmat Tuhanmu yang manakah yang kamu dustakan?"
	},
	{
		"aid": "62",
		"p": "op",
		"text": "Dan selain dari dua surga itu ada dua surga lagi."
	},
	{
		"aid": "63",
		"text": "Maka nikmat Tuhanmu yang manakah yang kamu dustakan?"
	},
	{
		"aid": "64",
		"p": "nl",
		"text": "Kedua surga itu [kelihatan] hijau tua warnanya."
	},
	{
		"aid": "65",
		"text": "Maka nikmat Tuhanmu yang manakah yang kamu dustakan?"
	},
	{
		"aid": "66",
		"p": "nl",
		"text": "Di dalam keduanya (surga itu) ada dua buah mata air yang memancar."
	},
	{
		"aid": "67",
		"text": "Maka nikmat Tuhanmu yang manakah yang kamu dustakan?"
	},
	{
		"aid": "68",
		"p": "nl",
		"text": "Di dalam kedua surga itu ada buah-buahan, kurma, dan delima."
	},
	{
		"aid": "69",
		"p": "cp",
		"text": "Maka nikmat Tuhanmu yang manakah yang kamu dustakan?"
	},
	{
		"aid": "70",
		"p": "op",
		"text": "Di dalam surga-surga itu ada bidadari-bidadari yang baik-baik dan jelita."
	},
	{
		"aid": "71",
		"text": "Maka nikmat Tuhanmu yang manakah yang kamu dustakan?"
	},
	{
		"aid": "72",
		"p": "nl",
		"text": "Bidadari-bidadari yang dipelihara di dalam kemah-kemah."
	},
	{
		"aid": "73",
		"text": "Maka nikmat Tuhanmu yang manakah yang kamu dustakan?"
	},
	{
		"aid": "74",
		"p": "nl",
		"text": "Mereka sebelumnya tidak pernah disentuh oleh manusia maupun oleh jin."
	},
	{
		"aid": "75",
		"text": "Maka nikmat Tuhanmu yang manakah yang kamu dustakan?"
	},
	{
		"aid": "76",
		"p": "nl",
		"text": "Mereka bersandar pada bantal-bantal yang hijau dan permadani-permadani yang indah."
	},
	{
		"aid": "77",
		"p": "cp",
		"text": "Maka nikmat Tuhanmu yang manakah yang kamu dustakan?"
	},
	{
		"aid": "78",
		"r": "3",
		"text": "Mahasuci nama Tuhanmu Pemilik Keagungan dan Kemuliaan."
	}
]
